tempmail/__init__.py
tempmail/src/__init__.py
tempmail/src/constants.py
tempmail/src/tempmail.py
tempmail/src/type_dict.py
tempmail_python3-0.1.3.dist-info/LICENSE
tempmail_python3-0.1.3.dist-info/METADATA
tempmail_python3-0.1.3.dist-info/WHEEL
tempmail_python3-0.1.3.dist-info/top_level.txt
tempmail_python3-0.1.3.dist-info/RECORD
